anysocks/__init__.py
anysocks/client.py
anysocks/exceptions.py
anysocks/meta.py
anysocks/websocket.py
anysocks-0.2.2.dist-info/LICENSE
anysocks-0.2.2.dist-info/METADATA
anysocks-0.2.2.dist-info/WHEEL
anysocks-0.2.2.dist-info/top_level.txt
anysocks-0.2.2.dist-info/RECORD
