Metadata-Version: 2.1
Name: anysocks
Version: 0.2.2
Summary: WebSocket protocol implementation for anyio
Home-page: https://github.com/clamor-py/anysocks
Author: Valentin B.
Author-email: valentin.be@protonmail.com
License: MIT
Project-URL: Documentation, https://anysocks.readthedocs.io/en/latest
Project-URL: Source, https://github.com/clamor-py/anysocks
Project-URL: Issue tracker, https://github.com/clamor-py/anysocks/issues
Keywords: anysocks websockets websocket client library anyio
Platform: UNKNOWN
Classifier: Development Status :: 5 - Production/Stable
Classifier: Intended Audience :: Developers
Classifier: License :: OSI Approved :: MIT License
Classifier: Operating System :: OS Independent
Classifier: Programming Language :: Python
Classifier: Programming Language :: Python :: 3.5
Classifier: Programming Language :: Python :: 3.6
Classifier: Programming Language :: Python :: 3.7
Classifier: Programming Language :: Python :: Implementation :: CPython
Classifier: Programming Language :: Python :: Implementation :: PyPy
Classifier: Environment :: Web Environment
Classifier: Topic :: Communications
Classifier: Topic :: Software Development :: Libraries :: Python Modules
Requires-Python: >=3.5.0
Requires-Dist: async-generator (==1.10)
Requires-Dist: anyio (==1.2.1)
Requires-Dist: wsproto (==0.14.1)
Requires-Dist: yarl (==1.4.2)
